MANIFEST.in
README.rst
setup.py
docs/HISTORY.rst
docs/INSTALL.txt
docs/LICENSE.GPL
docs/LICENSE.txt
redturtle/__init__.py
redturtle.video.egg-info/PKG-INFO
redturtle.video.egg-info/SOURCES.txt
redturtle.video.egg-info/dependency_links.txt
redturtle.video.egg-info/entry_points.txt
redturtle.video.egg-info/namespace_packages.txt
redturtle.video.egg-info/not-zip-safe
redturtle.video.egg-info/requires.txt
redturtle.video.egg-info/top_level.txt
redturtle/video/README.txt
redturtle/video/__init__.py
redturtle/video/config.py
redturtle/video/configure.zcml
redturtle/video/events.py
redturtle/video/extender.py
redturtle/video/metadataextractor.py
redturtle/video/migrator.py
redturtle/video/rebuild.sh
redturtle/video/remote_thumb.py
redturtle/video/setuphandlers.py
redturtle/video/Extensions/install.py
redturtle/video/browser/__init__.py
redturtle/video/browser/basevideoembedcode_template.pt
redturtle/video/browser/configure.zcml
redturtle/video/browser/fl-play.css
redturtle/video/browser/fpPlayButtonBig.png
redturtle/video/browser/link_view.pt
redturtle/video/browser/migrateblobs.py
redturtle/video/browser/migrateflowplayable.py
redturtle/video/browser/redturtlevideo_macros.pt
redturtle/video/browser/video_view.pt
redturtle/video/browser/videoembedcode.py
redturtle/video/browser/view.py
redturtle/video/content/__init__.py
redturtle/video/content/configure.zcml
redturtle/video/content/default.py
redturtle/video/content/rtinternalvideo.py
redturtle/video/content/rtremotevideo.py
redturtle/video/content/video_schema.py
redturtle/video/i18n/plone-it.po
redturtle/video/i18n/plone-manual.pot
redturtle/video/i18n/plone.pot
redturtle/video/interfaces/__init__.py
redturtle/video/interfaces/rtinternalvideo.py
redturtle/video/interfaces/rtremotevideo.py
redturtle/video/interfaces/video.py
redturtle/video/interfaces/videoembedcode.py
redturtle/video/locales/.plone.pot
redturtle/video/locales/redturtle.video-manual.pot
redturtle/video/locales/redturtle.video.pot
redturtle/video/locales/es/LC_MESSAGES/redturtle.video.mo
redturtle/video/locales/es/LC_MESSAGES/redturtle.video.po
redturtle/video/locales/it/LC_MESSAGES/redturtle.video.mo
redturtle/video/locales/it/LC_MESSAGES/redturtle.video.po
redturtle/video/portlets/__init__.py
redturtle/video/portlets/configure.zcml
redturtle/video/portlets/portlet.pt
