Metadata-Version: 1.0
Name: redturtle.video
Version: 1.1.1
Summary: Video content types for Plone; use collective.flowplayer but also pluggable with external services. - Forward compatibility shim version, for easily migrate to wildcard.media
Home-page: http://plone.org/products/redturtle.video
Author: RedTurtle Technology
Author-email: sviluppoplone@redturtle.it
License: GPL
Keywords: plone video flowplayer plonegov
Platform: UNKNOWN
Classifier: Framework :: Plone
Classifier: Framework :: Plone :: 3.3
Classifier: Framework :: Plone :: 4.0
Classifier: Framework :: Plone :: 4.1
Classifier: Framework :: Plone :: 4.2
Classifier: Framework :: Plone :: 4.3
Classifier: Development Status :: 5 - Production/Stable
Classifier: Topic :: Multimedia :: Video
Classifier: License :: OSI Approved :: GNU General Public License (GPL)
